growthbook/__init__.py
growthbook/common_types.py
growthbook/core.py
growthbook/growthbook.py
growthbook/growthbook_client.py
growthbook/py.typed
growthbook/plugins/__init__.py
growthbook/plugins/base.py
growthbook/plugins/growthbook_tracking.py
growthbook/plugins/request_context.py
growthbook-2.0.0.dist-info/licenses/LICENSE
growthbook-2.0.0.dist-info/METADATA
growthbook-2.0.0.dist-info/WHEEL
growthbook-2.0.0.dist-info/top_level.txt
growthbook-2.0.0.dist-info/RECORD
