Metadata-Version: 2.4
Name: growthbook
Version: 2.0.0
Summary: Powerful Feature flagging and A/B testing for Python apps
Home-page: https://github.com/growthbook/growthbook-python
Author: GrowthBook
Author-email: GrowthBook <hello@growthbook.io>
License: MIT
Keywords: growthbook
Classifier: Development Status :: 4 - Beta
Classifier: Intended Audience :: Developers
Classifier: License :: OSI Approved :: MIT License
Classifier: Programming Language :: Python :: 3
Classifier: Programming Language :: Python :: 3.6
Classifier: Programming Language :: Python :: 3.7
Classifier: Programming Language :: Python :: 3.8
Classifier: Programming Language :: Python :: 3.9
Classifier: Programming Language :: Python :: 3.10
Classifier: Programming Language :: Python :: 3.11
Classifier: Programming Language :: Python :: 3.12
Classifier: Typing :: Typed
Requires-Python: >=3.7
License-File: LICENSE
Requires-Dist: cryptography
Requires-Dist: typing_extensions
Requires-Dist: urllib3
Requires-Dist: dataclasses; python_version < "3.7"
Requires-Dist: async-generator; python_version < "3.7"
Requires-Dist: aiohttp>=3.6.0
Requires-Dist: importlib-metadata; python_version < "3.8"
Dynamic: author
Dynamic: home-page
Dynamic: license-file
Dynamic: requires-python
